TColorP/TColorP.py
TColorP/__init__.py
tColorP-0.0.2.dist-info/LICENSE
tColorP-0.0.2.dist-info/METADATA
tColorP-0.0.2.dist-info/WHEEL
tColorP-0.0.2.dist-info/top_level.txt
tColorP-0.0.2.dist-info/RECORD
