Metadata-Version: 2.1
Name: tColorP
Version: 0.0.2
Summary: print with color
Home-page: https://github.com/ruxia-TJY/TColorP
Author: ruxia-TJY
Author-email: ruxia.tjy@qq.com
License: MIT
Download-URL: https://github.com/ruxia-TJY/TColorP
Project-URL: Bug Tracker, https://github.com/ruxia-TJY/TColorP/issues
Keywords: print with color
Platform: UNKNOWN
Classifier: Programming Language :: Python :: 3
Classifier: Operating System :: MacOS
Classifier: Operating System :: POSIX :: Linux
Classifier: Operating System :: Microsoft :: Windows
Classifier: License :: OSI Approved :: MIT License
Requires-Python: >=3
